urlimage/__init__.py
urlimage/urlimage.py
urlimage_dcollien-0.0.1.dist-info/LICENSE
urlimage_dcollien-0.0.1.dist-info/METADATA
urlimage_dcollien-0.0.1.dist-info/WHEEL
urlimage_dcollien-0.0.1.dist-info/top_level.txt
urlimage_dcollien-0.0.1.dist-info/RECORD
