Metadata-Version: 2.1
Name: urlimage-dcollien
Version: 0.0.1
Summary: Infers an image to use for a given URL
Home-page: https://github.com/dcollien/urlimage
Author: David Collien
Author-email: me@dcollien.com
License: UNKNOWN
Platform: UNKNOWN
Classifier: Programming Language :: Python :: 3
Classifier: License :: OSI Approved :: MIT License
Classifier: Operating System :: OS Independent
Requires-Python: >=3.6
